city_score/__init__.py
city_score/__version__.py
city_score/app.py
city_score/cache.py
city_score/city.py
city_score/decorators.py
city_score/printers.py
city_score/source.py
city_score/sources/__init__.py
city_score/sources/core.py
city_score/sources/peopleforbikes.py
city_score/sources/skicentral.py
city_score/sources/snowpak.py
city_score/sources/traillink.py
city_score/sources/yelp.py
city_score/sources/zillow.py
city_score-0.2.0.dist-info/LICENSE
city_score-0.2.0.dist-info/METADATA
city_score-0.2.0.dist-info/WHEEL
city_score-0.2.0.dist-info/top_level.txt
city_score-0.2.0.dist-info/RECORD
