Metadata-Version: 2.1
Name: city-score
Version: 0.2.0
Summary: A command-line application for scoring US cities and towns.
Maintainer-email: Jacob Budin <self@jacobbudin.com>
License: The MIT License
Keywords: cli,geography,reading,epub,instapaper
Classifier: Development Status :: 4 - Beta
Classifier: Environment :: Console
Classifier: Intended Audience :: End Users/Desktop
Classifier: License :: OSI Approved :: MIT License
Classifier: Natural Language :: English
Classifier: Programming Language :: Python
Classifier: Programming Language :: Python :: 3
Classifier: Programming Language :: Python :: 3.7
Classifier: Programming Language :: Python :: 3.8
Classifier: Programming Language :: Python :: 3.9
Classifier: Programming Language :: Python :: 3.10
Classifier: Programming Language :: Python :: 3.11
Requires-Python: >=3.7
License-File: LICENSE
Requires-Dist: diskcache (>=5.6.1)
Requires-Dist: geopy (>=2.3.0)
Requires-Dist: requests (>=2.31.0)
Requires-Dist: rich (>=13.4.2)
Requires-Dist: yelpapi (>=2.5.0)
